flake8/__init__.py
flake8/__main__.py
flake8/_compat.py
flake8/checker.py
flake8/defaults.py
flake8/exceptions.py
flake8/processor.py
flake8/statistics.py
flake8/style_guide.py
flake8/utils.py
flake8/api/__init__.py
flake8/api/legacy.py
flake8/formatting/__init__.py
flake8/formatting/base.py
flake8/formatting/default.py
flake8/main/__init__.py
flake8/main/application.py
flake8/main/cli.py
flake8/main/debug.py
flake8/main/options.py
flake8/options/__init__.py
flake8/options/aggregator.py
flake8/options/config.py
flake8/options/manager.py
flake8/plugins/__init__.py
flake8/plugins/manager.py
flake8/plugins/pyflakes.py
flake82-3.9.2.dist-info/LICENSE
flake82-3.9.2.dist-info/METADATA
flake82-3.9.2.dist-info/WHEEL
flake82-3.9.2.dist-info/entry_points.txt
flake82-3.9.2.dist-info/top_level.txt
flake82-3.9.2.dist-info/RECORD
