Metadata-Version: 2.1
Name: flake82
Version: 3.9.2
Summary: the modular source code checker: pep8 pyflakes and co with pyproject.toml support
Home-page: https://github.com/eganjs/flake8
Author: Tarek Ziade
Author-email: tarek@ziade.org
Maintainer: Ian Stapleton Cordasco
Maintainer-email: graffatcolmingov@gmail.com
License: MIT
Platform: UNKNOWN
Classifier: Development Status :: 5 - Production/Stable
Classifier: Environment :: Console
Classifier: Framework :: Flake8
Classifier: Intended Audience :: Developers
Classifier: License :: OSI Approved :: MIT License
Classifier: Programming Language :: Python
Classifier: Programming Language :: Python :: 3
Classifier: Programming Language :: Python :: 3.6
Classifier: Programming Language :: Python :: 3.7
Classifier: Programming Language :: Python :: 3.8
Classifier: Programming Language :: Python :: 3.9
Classifier: Topic :: Software Development :: Libraries :: Python Modules
Classifier: Topic :: Software Development :: Quality Assurance
Requires-Python: >=3.6
Requires-Dist: pyflakes (<2.4.0,>=2.3.0)
Requires-Dist: pycodestyle (<2.8.0,>=2.7.0)
Requires-Dist: mccabe (<0.7.0,>=0.6.0)
Requires-Dist: toml
Requires-Dist: importlib-metadata ; python_version < "3.8"
